{
    "counting": {
        "total": {
            "leaderboard": {
                "first": [],
                "second": [],
                "third": []
            },
            "individual_count":{
            }
        },
        "decimal": {
            "leaderboard": {
                "first": [],
                "second": [],
                "third": []
            },
            "individual_count":{
            }
        },
        "binary": {
            "leaderboard": {
                "first": [],
                "second": [],
                "third": []
            },
            "individual_count":{
            }
        }
    }
}